langchoice/__init__.py
langchoice/common.py
langchoice/langchoice.py
langchoice/lc_test.py
langchoice/out.txt
langchoice-0.0.3.dist-info/LICENSE
langchoice-0.0.3.dist-info/METADATA
langchoice-0.0.3.dist-info/WHEEL
langchoice-0.0.3.dist-info/RECORD
