Metadata-Version: 2.1
Name: langchoice
Version: 0.0.3
Summary: switch-case over free-form sentences.
Home-page: https://github.com/ekshaks/langchoice
License: Apache License, Version 2.0
Keywords: LLM,QA,IR,embeddings,switch-case,if-then-else
Author: Nishant Sinha
Author-email: nishant@offnote.co
Requires-Python: >=3.10
Classifier: License :: Other/Proprietary License
Classifier: Programming Language :: Python :: 3
Classifier: Programming Language :: Python :: 3.10
Classifier: Programming Language :: Python :: 3.11
Project-URL: Repository, https://github.com/ekshaks/langchoice
